snapcfg/__init__.py
snapcfg/__main__.py
snapcfg/cli.py
snapcfg/loader.py
snapcfg/schema_parser.py
snapcfg/validator.py
snapcfg-0.1.1.dist-info/licenses/LICENSE
snapcfg-0.1.1.dist-info/METADATA
snapcfg-0.1.1.dist-info/WHEEL
snapcfg-0.1.1.dist-info/entry_points.txt
snapcfg-0.1.1.dist-info/top_level.txt
snapcfg-0.1.1.dist-info/RECORD
