Metadata-Version: 2.4
Name: snapcfg
Version: 0.1.1
Summary: Validate configs against a flexible app-defined schema.
Author: PJ Hayes
Author-email: archood2next@gmail.com
License: MPL-2.0
Classifier: Programming Language :: Python :: 3
Classifier: License :: OSI Approved :: Mozilla Public License 2.0 (MPL 2.0)
Requires-Python: >=3.6
License-File: LICENSE
Requires-Dist: pyyaml
Requires-Dist: typer
Requires-Dist: rich
Requires-Dist: snaparg
Dynamic: author
Dynamic: author-email
Dynamic: classifier
Dynamic: description
Dynamic: description-content-type
Dynamic: license
Dynamic: license-file
Dynamic: requires-dist
Dynamic: requires-python
Dynamic: summary
